asgar/__init__.py
asgar/multiplication.py
asgar-0.1.0.dist-info/LICENSE
asgar-0.1.0.dist-info/METADATA
asgar-0.1.0.dist-info/WHEEL
asgar-0.1.0.dist-info/top_level.txt
asgar-0.1.0.dist-info/RECORD
