Metadata-Version: 2.1
Name: asgar
Version: 0.1.0
Summary: Android GUI Screen Analyzer
Home-page: https://medium-multiply.readthedocs.io/
Author: Navid Salehnamadi
Author-email: navid.saleh.n@gmail.com
License: GPL3
Platform: UNKNOWN
Classifier: Intended Audience :: Developers
Classifier: License :: OSI Approved :: MIT License
Classifier: Programming Language :: Python
Classifier: Programming Language :: Python :: 3.7
Classifier: Programming Language :: Python :: 3.8
Classifier: Programming Language :: Python :: 3.9
Classifier: Operating System :: OS Independent
Requires-Dist: numpy (==1.21.4)
